boon.py
boon_term-0.0.0.dist-info/LICENSE
boon_term-0.0.0.dist-info/METADATA
boon_term-0.0.0.dist-info/WHEEL
boon_term-0.0.0.dist-info/top_level.txt
boon_term-0.0.0.dist-info/RECORD
