Metadata-Version: 2.1
Name: boon-term
Version: 0.0.0
Summary: unix terminal framework
Author-email: Tobias Bengfort <tobias.bengfort@posteo.de>
License: MIT
Project-URL: Homepage, https://github.com/xi/boon
Classifier: Environment :: Console :: Curses
Classifier: Intended Audience :: Developers
Classifier: Operating System :: POSIX :: Linux
Classifier: Programming Language :: Python
Classifier: License :: OSI Approved :: MIT License
Classifier: Topic :: Software Development :: User Interfaces
License-File: LICENSE
